{
  "generated": "2026-01-28T06:09:41.137Z",
  "totals": {
    "year2024": 8286,
    "year2025": 10764,
    "year2026": 664
  },
  "last30Days": {
    "plugins": 746,
    "themes": 149,
    "core": 0,
    "total": 895
  },
  "recentVulns": [
    {
      "id": "bb0e77e1-7e9f-4f7e-8953-c86ab0e5ae7a",
      "name": "Simple User Registration <= 6.7 - Authenticated (Subscriber+) Privilege Escalation via profile_save_field",
      "severity": "high",
      "type": "plugin",
      "software": "Simple User Registration",
      "published": "2026-01-27 21:50:50",
      "cvssScore": 8.8
    },
    {
      "id": "e739e7d3-756a-4c93-9ca7-f7b9f9657033",
      "name": "Frontend File Manager Plugin <= 23.5 - Missing Authorization to Unauthenticated Arbitrary File Sharing via 'file_id' Parameter",
      "severity": "high",
      "type": "plugin",
      "software": "Frontend File Manager Plugin",
      "published": "2026-01-27 21:50:20",
      "cvssScore": 7.5
    },
    {
      "id": "cb02878a-2c85-4dcb-bdc0-e65addf9fb9c",
      "name": "TelSender <= 1.14.14 - Unauthenticated Stored Cross-Site Scripting via Telegram Chat Title",
      "severity": "high",
      "type": "plugin",
      "software": "TelSender – Wp to telegram  СF 7, Events, Wpforms, Ninja forms, Wooccommerce",
      "published": "2026-01-27 21:48:26",
      "cvssScore": 7.2
    },
    {
      "id": "6f63d2c4-cbae-4177-8494-daca96449ecc",
      "name": "Search Atlas SEO – Premier SEO Plugin for One-Click WP Publishing & Integrated AI Optimization 2.4.4 - 2.5.12 - Missing Authorization to Authenticated (Subscriber+) Authentication Bypass via Account Takeover",
      "severity": "high",
      "type": "plugin",
      "software": "Search Atlas SEO – Premier SEO Plugin for One-Click WP Publishing & Integrated AI Optimization",
      "published": "2026-01-27 21:31:02",
      "cvssScore": 8.8
    },
    {
      "id": "d5227269-4406-4fcf-af37-f1db0af857d6",
      "name": "AI Engine <= 3.3.2 - Authenticated (Editor+) Arbitrary File Upload via 'filename' Parameter in update_media_metadata Endpoint",
      "severity": "high",
      "type": "plugin",
      "software": "AI Engine – The Chatbot and AI Framework for WordPress",
      "published": "2026-01-27 19:28:10",
      "cvssScore": 7.2
    },
    {
      "id": "f86a69ab-2fc5-4c84-872b-929dbec429cd",
      "name": "New User Approve <= 3.2.2 - Missing Authorization to Unauthenticated Arbitrary User Approval, Denial, and Information Disclosure",
      "severity": "high",
      "type": "plugin",
      "software": "New User Approve",
      "published": "2026-01-27 17:49:02",
      "cvssScore": 7.3
    },
    {
      "id": "ef07d6b0-ccdb-4b33-817f-6d4b3ad96243",
      "name": "TableMaster for Elementor <= 1.3.6 - Authenticated (Author+) Server-Side Request Forgery via 'csv_url' Parameter",
      "severity": "high",
      "type": "plugin",
      "software": "TableMaster for Elementor – Advanced Responsive Tables for Elementor",
      "published": "2026-01-27 17:21:05",
      "cvssScore": 7.2
    },
    {
      "id": "37a8642d-07f5-4b1b-8419-e30589089162",
      "name": "Snow Monkey Forms <= 12.0.3 - Unauthenticated Arbitrary File Deletion via Path Traversal",
      "severity": "critical",
      "type": "plugin",
      "software": "Snow Monkey Forms",
      "published": "2026-01-27 00:00:00",
      "cvssScore": 9.8
    },
    {
      "id": "a61d8d2a-742f-45f1-9146-f733b80ef195",
      "name": "VidShop – Shoppable Videos for WooCommerce <= 1.1.4 - Unauthenticated Time-Based SQL Injection via 'fields'",
      "severity": "high",
      "type": "plugin",
      "software": "VidShop – Shoppable Videos for WooCommerce",
      "published": "2026-01-27 00:00:00",
      "cvssScore": 7.5
    },
    {
      "id": "d328e059-7235-496d-9c5a-c394df7ad235",
      "name": "AhaChat Messenger Marketing <= 1.1 - Unauthenticated Stored Cross-Site Scripting",
      "severity": "high",
      "type": "plugin",
      "software": "AhaChat Messenger Marketing",
      "published": "2026-01-27 00:00:00",
      "cvssScore": 7.2
    }
  ],
  "bySeverity": {
    "critical": 2440,
    "high": 5966,
    "medium": 24658,
    "low": 141
  }
}